README.md
setup.py
pog/__init__.py
pog/cli.py
pog/cloud_cleanup.py
pog/create_keypair.py
pog/pog.py
pog/fs/__init__.py
pog/fs/b2fs.py
pog/fs/localfs.py
pog/fs/pogfs.py
pog/fs/s3fs.py
pog/lib/__init__.py
pog/lib/background_work.py
pog/lib/blob_store.py
pog/lib/local_file_list.py
pog/lib/secret.py
pog/scripts/b2-save.sh
pog/scripts/local-save.sh
pog/scripts/s3-save.sh
pogcli.egg-info/PKG-INFO
pogcli.egg-info/SOURCES.txt
pogcli.egg-info/dependency_links.txt
pogcli.egg-info/entry_points.txt
pogcli.egg-info/requires.txt
pogcli.egg-info/top_level.txt