Metadata-Version: 2.1
Name: pogcli
Version: 0.1.4
Summary: File encryption and backup utility
Home-page: https://github.com/sz3/pog
Author: Stephen Zimmerman
Author-email: sz@galacticicecube.com
License: MIT
Platform: UNKNOWN
Classifier: License :: OSI Approved :: MIT License
Classifier: Programming Language :: Python :: 3
Classifier: Programming Language :: Python :: 3.6
Classifier: Programming Language :: Python :: 3.7
Classifier: Programming Language :: Python :: 3.8
Requires-Python: >=3.6
Provides-Extra: b2
Provides-Extra: s3
